Metadata-Version: 2.1
Name: streamlit-imp-scenario-pages-with-msal
Version: 0.0.1
Summary: UNKNOWN
Home-page: UNKNOWN
Author: 
Author-email: 
License: UNKNOWN
Platform: UNKNOWN
Requires-Python: >=3.6
Requires-Dist: streamlit (>=1.36)
